atro_pyrsync/__init__.py
atro_pyrsync/helpers.py
atro_pyrsync-0.0.8.dist-info/METADATA
atro_pyrsync-0.0.8.dist-info/WHEEL
atro_pyrsync-0.0.8.dist-info/RECORD
